betterconf/__init__.py
betterconf/_config.py
betterconf/_field.py
betterconf/_specials.py
betterconf/caster.py
betterconf/decorator.py
betterconf/exceptions.py
betterconf/provider.py
betterconf/py.typed
betterconf-4.5.0.dist-info/LICENSE
betterconf-4.5.0.dist-info/METADATA
betterconf-4.5.0.dist-info/WHEEL
betterconf-4.5.0.dist-info/RECORD
