Metadata-Version: 2.1
Name: betterconf
Version: 4.5.0
Summary: Configs in Python made smooth and simple
Home-page: https://github.com/prostomarkeloff/betterconf
License: MIT
Keywords: configs,config,env,.env
Author: prostomarkeloff
Requires-Python: >=3.11,<4.0
Classifier: License :: OSI Approved :: MIT License
Classifier: Programming Language :: Python :: 3
Classifier: Programming Language :: Python :: 3.11
Classifier: Programming Language :: Python :: 3.12
Classifier: Topic :: Software Development :: Libraries :: Python Modules
Project-URL: Documentation, https://github.com/prostomarkeloff/betterconf
Project-URL: Repository, https://github.com/prostomarkeloff/betterconf
